Workbook

Sheet Assumptions
B1: PICKLEBALL COURT - INVESTMENT ASSUMPTIONS (INPUTS)
B3: CAPEX (เงินลงทุนก่อสร้าง)
B4: Construction Cost | C4: 3000000 | D4: THB
B5: Contingency % | C5: 0.1 | D5: % | E5: Assumption: 10% of construction cost
C6: =(C4*C5)+C4 -> 3300000
B7: OPEX ต่อเดือน (Monthly Operating Expenses)
B8: Salaries | C8: 50000 | D8: THB/mo
B9: Facilities / Utilities | C9: 80000 | D9: THB/mo
B10: Land Rent / Lease | C10: 150000 | D10: THB/mo
B11: Miscellaneous | C11: 25000 | D11: THB/mo
B13: Revenue Assumptions - Professional Courts
B14: Hourly Rate per Court | C14: 700 | D14: THB/hr
B15: Avg Utilization per Court | C15: 6 | D15: hrs/day | E15: 4pm-9pm peak time
B16: Number of Courts | C16: 3 | D16: courts
C17: =(C14*C15*C16)*E17 -> 12600 | D17: THB/day | E17: 1
B19: Revenue Assumptions - Standard Courts
B20: Hourly Rate per Court | C20: 400 | D20: THB/hr
B21: Avg Utilization per Court | C21: 6 | D21: hrs/day | E21: 4pm-9pm peak time
B22: Number of Courts | C22: 2 | D22: courts
B23: Standard Daily Revenue (AS STATED IN SOURCE FILE) | C23: =(C20*C21*C22)*E23 -> 4800 | D23: THB/day | E23: 1
B25: Revenue Assumptions - Simulator Courts
B26: Hourly Rate per Court | C26: 300 | D26: THB/hr
B27: Avg Utilization per Court | C27: 6 | D27: hrs/day | E27: 4pm-9pm peak time
B28: Number of Courts | C28: 2 | D28: courts
B29: Standard Daily Revenue (AS STATED IN SOURCE FILE) | C29: =(C26*C27*C28)*E29 -> 3600 | D29: THB/day | E29: 1
B31: Total Daily all Courts Revenue | C31: =C17+C23+C29 -> 21000 | D31: THB/day
B33: Other Assumptions
B34: Days per Month | C34: 30 | D34: days
B35: Months per Year | C35: 12 | D35: months
B36: Discount Rate (WACC assumption) | C36: 0.1 | D36: %/yr | E36: ASSUMPTION - ไม่มีในไฟล์ต้นฉบับ ใช้ค่ากลางสำหรับโครงการ SME
B37: Projection Horizon | C37: 5 | D37: years

Sheet Calc - As Filed
B1: SCENARIO 1: AS FILED (ตามไฟล์ต้นฉบับ)
B3: CAPEX
B4: Total CAPEX | C4: =Assumptions!$C$4*(1+Assumptions!$C$5) -> 3300000 | D4: THB
B6: Daily Revenue
B7: Professional Courts Daily Revenue | C7: =Assumptions!C17 -> 12600 | D7: THB/day
B8: Standard Courts Daily Revenue | C8: =Assumptions!C23 -> 4800 | D8: THB/day
B9: Simulator Courts Daily Revenue | C9: =Assumptions!C29 -> 3600 | D9: THB/day
B10: Total Daily Revenue | C10: =SUM(C7:C9) -> 21000 | D10: THB/day
B12: Monthly / Annual P&L
B13: Monthly OPEX | C13: =Assumptions!$C$8+Assumptions!$C$9+Assumptions!$C$10+Assumptions!$C$11 -> 305000 | D13: THB
B14: Monthly Gross Revenue | C14: =C10*Assumptions!$C$34 -> 630000 | D14: THB
B15: Monthly Net Profit | C15: =C14-C13 -> 325000 | D15: THB
B16: Annual Gross Revenue | C16: =C14*Assumptions!$C$35 -> 7560000 | D16: THB
B17: Annual OPEX | C17: =C13*Assumptions!$C$35 -> 3660000 | D17: THB
B18: Annual EBITDA (Net Profit) | C18: =C16-C17 -> 3900000 | D18: THB
B20: Investor Feasibility Indicators
B21: EBITDA Margin % | C21: =C18/C16 -> 0.51587302
B22: Accounting ROI (Year 1) % | C22: =C18/C4 -> 1.1818182
B23: Payback Period (Months) | C23: =C4/C15 -> 10.153846
B24: Payback Period (Years) | C24: =C23/12 -> 0.84615385
B26: Dynamic Break-Even Analysis
B27: Daily Revenue Needed to Break Even | C27: =C13/Assumptions!$C$34 -> 10166.667 | D27: THB
B28: Blended Rate per Hour (all courts) | C28: =C10/((Assumptions!$C$15*Assumptions!$C$16)+(Assumptions!$C$21*Assumptions!$C$22)) -> 700 | D28: THB/hr
B29: Break-Even Hours Needed (Total, all courts/day) | C29: =C27/C28 -> 14.52381 | D29: hrs
B30: Break-Even Hours Needed per Court/Day | C30: =C29/(Assumptions!$C$16+Assumptions!$C$22) -> 2.9047619 | D30: hrs
B31: Utilization Needed to Break Even % | C31: =C30/Assumptions!$C$15 -> 0.48412698

Sheet Calc - Reconciled
B1: SCENARIO 2: RECONCILED (ตามสูตร Rate x Hours x Courts จริง) - แนะนำให้ใช้
B3: CAPEX
B4: Total CAPEX | C4: =Assumptions!$C$4*(1+Assumptions!$C$5) -> 3300000 | D4: THB
B6: Daily Revenue
B7: Professional Courts Daily Revenue | C7: ='Calc - As Filed'!C7*E7 -> 9450 | D7: THB/day | E7: 0.75
B8: Standard Courts Daily Revenue | C8: ='Calc - As Filed'!C8*E8 -> 3120 | D8: THB/day | E8: 0.65
B9: Standard Courts Daily Revenue | C9: ='Calc - As Filed'!C9*E9 -> 1800 | D9: THB/day | E9: 0.5
B10: Total Daily Revenue | C10: =SUM(C7:C9) -> 14370 | D10: THB/day
B12: Monthly / Annual P&L
B13: Monthly OPEX | C13: =Assumptions!$C$8+Assumptions!$C$9+Assumptions!$C$10+Assumptions!$C$11 -> 305000 | D13: THB
B14: Monthly Gross Revenue | C14: =C10*Assumptions!$C$34 -> 431100 | D14: THB
B15: Monthly Net Profit | C15: =C14-C13 -> 126100 | D15: THB
B16: Annual Gross Revenue | C16: =C14*Assumptions!$C$35 -> 5173200 | D16: THB
B17: Annual OPEX | C17: =C13*Assumptions!$C$35 -> 3660000 | D17: THB
B18: Annual EBITDA (Net Profit) | C18: =C16-C17 -> 1513200 | D18: THB
B20: Investor Feasibility Indicators
B21: EBITDA Margin % | C21: =C18/C16 -> 0.29250754
B22: Accounting ROI (Year 1) % | C22: =C18/C4 -> 0.45854545
B23: Payback Period (Months) | C23: =C4/C15 -> 26.169707
B24: Payback Period (Years) | C24: =C23/12 -> 2.1808089
B26: Dynamic Break-Even Analysis
B27: Daily Revenue Needed to Break Even | C27: =C13/Assumptions!$C$34 -> 10166.667 | D27: THB
B28: Blended Rate per Hour (all courts) | C28: =C10/((Assumptions!$C$15*Assumptions!$C$16)+(Assumptions!$C$21*Assumptions!$C$22)) -> 479 | D28: THB/hr
B29: Break-Even Hours Needed (Total, all courts/day) | C29: =C27/C28 -> 21.224774 | D29: hrs
B30: Break-Even Hours Needed per Court/Day | C30: =C29/(Assumptions!$C$16+Assumptions!$C$22) -> 4.2449548 | D30: hrs
B31: Utilization Needed to Break Even % | C31: =C30/Assumptions!$C$15 -> 0.70749246

Sheet Scenario Comparison
B1: SCENARIO COMPARISON - AS FILED vs RECONCILED
B3: Indicator | C3: As Filed | D3: Reconciled | E3: Note
B4: Total Daily Revenue (THB/day) | C4: ='Calc - As Filed'!C10 -> 21000 | D4: ='Calc - Reconciled'!C10 -> 14370
B5: Monthly Gross Revenue (THB) | C5: ='Calc - As Filed'!C14 -> 630000 | D5: ='Calc - Reconciled'!C14 -> 431100
B6: Monthly Net Profit (THB) | C6: ='Calc - As Filed'!C15 -> 325000 | D6: ='Calc - Reconciled'!C15 -> 126100
B7: Annual EBITDA (THB) | C7: ='Calc - As Filed'!C18 -> 3900000 | D7: ='Calc - Reconciled'!C18 -> 1513200
B8: EBITDA Margin % | C8: ='Calc - As Filed'!C21 -> 0.51587302 | D8: ='Calc - Reconciled'!C21 -> 0.29250754
B9: Accounting ROI Year 1 % | C9: ='Calc - As Filed'!C22 -> 1.1818182 | D9: ='Calc - Reconciled'!C22 -> 0.45854545
B10: Payback Period (Months) | C10: ='Calc - As Filed'!C23 -> 10.153846 | D10: ='Calc - Reconciled'!C23 -> 26.169707
B11: Break-Even Utilization % | C11: ='Calc - As Filed'!C31 -> 0.48412698 | D11: ='Calc - Reconciled'!C31 -> 0.70749246 | E11: ยึด Reconciled เป็นฐานเจรจากับผู้ถือหุ้น

Sheet Sensitivity
B1: SENSITIVITY ANALYSIS - Utilization vs Returns (Reconciled Base)
B3: Base Daily Revenue @100% (link) | C3: ='Calc - Reconciled'!C10 -> 14370
B4: Monthly OPEX (link) | C4: ='Calc - Reconciled'!C13 -> 305000
B6: Utilization % | C6: Monthly Net (THB) | D6: Annual EBITDA (THB) | E6: ROI Yr1 % | F6: Payback (mo)
B7: 1 | C7: =$C$3*B7*Assumptions!$C$34-$C$4 -> 126100 | D7: =C7*12 -> 1513200 | E7: =D7/'Calc - Reconciled'!C4 -> 0.45854545 | F7: =IF(C7>0,'Calc - Reconciled'!C4/C7,"-") -> 26.169707
B8: 0.9 | C8: =$C$3*B8*Assumptions!$C$34-$C$4 -> 82990 | D8: =C8*12 -> 995880 | E8: =D8/'Calc - Reconciled'!C4 -> 0.30178182 | F8: =IF(C8>0,'Calc - Reconciled'!C4/C8,"-") -> 39.763827
B9: 0.8 | C9: =$C$3*B9*Assumptions!$C$34-$C$4 -> 39880 | D9: =C9*12 -> 478560 | E9: =D9/'Calc - Reconciled'!C4 -> 0.14501818 | F9: =IF(C9>0,'Calc - Reconciled'!C4/C9,"-") -> 82.748245
B10: 0.7 | C10: =$C$3*B10*Assumptions!$C$34-$C$4 -> -3230 | D10: =C10*12 -> -38760 | E10: =D10/'Calc - Reconciled'!C4 -> -0.011745455 | F10: =IF(C10>0,'Calc - Reconciled'!C4/C10,"-") -> -
B11: 0.63 | C11: =$C$3*B11*Assumptions!$C$34-$C$4 -> -33407 | D11: =C11*12 -> -400884 | E11: =D11/'Calc - Reconciled'!C4 -> -0.12148 | F11: =IF(C11>0,'Calc - Reconciled'!C4/C11,"-") -> -
B12: 0.6 | C12: =$C$3*B12*Assumptions!$C$34-$C$4 -> -46340 | D12: =C12*12 -> -556080 | E12: =D12/'Calc - Reconciled'!C4 -> -0.16850909 | F12: =IF(C12>0,'Calc - Reconciled'!C4/C12,"-") -> -
B13: 0.5 | C13: =$C$3*B13*Assumptions!$C$34-$C$4 -> -89450 | D13: =C13*12 -> -1073400 | E13: =D13/'Calc - Reconciled'!C4 -> -0.32527273 | F13: =IF(C13>0,'Calc - Reconciled'!C4/C13,"-") -> -
B14: 0.4 | C14: =$C$3*B14*Assumptions!$C$34-$C$4 -> -132560 | D14: =C14*12 -> -1590720 | E14: =D14/'Calc - Reconciled'!C4 -> -0.48203636 | F14: =IF(C14>0,'Calc - Reconciled'!C4/C14,"-") -> -
B15: 0.3 | C15: =$C$3*B15*Assumptions!$C$34-$C$4 -> -175670 | D15: =C15*12 -> -2108040 | E15: =D15/'Calc - Reconciled'!C4 -> -0.6388 | F15: =IF(C15>0,'Calc - Reconciled'!C4/C15,"-") -> -

Sheet 5Y DCF
B1: 5-YEAR CASH FLOW, NPV & IRR (Reconciled Scenario, no growth)
B3: Discount Rate (link) | C3: =Assumptions!$C$36 -> 0.1
B5: Year | C5: 0 | D5: 1 | E5: 2 | F5: 3 | G5: 4 | H5: 5
B6: Cash Flow (THB) | C6: =-'Calc - Reconciled'!C4 -> -3300000 | D6: ='Calc - Reconciled'!C18 -> 1513200 | E6: ='Calc - Reconciled'!C18 -> 1513200 | F6: ='Calc - Reconciled'!C18 -> 1513200 | G6: ='Calc - Reconciled'!C18 -> 1513200 | H6: ='Calc - Reconciled'!C18 -> 1513200
B7: Discounted Cash Flow | C7: =C6/(1+$C$3)^C5 -> -3300000 | D7: =D6/(1+$C$3)^D5 -> 1375636.4 | E7: =E6/(1+$C$3)^E5 -> 1250578.5 | F7: =F6/(1+$C$3)^F5 -> 1136889.6 | G7: =G6/(1+$C$3)^G5 -> 1033536 | H7: =H6/(1+$C$3)^H5 -> 939578.15
B9: NPV (sum of discounted CF) | C9: =SUM(C7:H7) -> 2436218.5
B10: IRR (5-year) | C10: =IRR(C6:H6) -> 0.35998176
B12: หมายเหตุ: ไม่มี growth ของรายได้, ไม่รวมภาษี/ดอกเบี้ย/ค่าเสื่อม (ไม่มีข้อมูลในไฟล์ต้นฉบับ), discount rate เป็น assumption
